django_http_debug/__init__.py
django_http_debug/admin.py
django_http_debug/middleware.py
django_http_debug/models.py
django_http_debug/views.py
django_http_debug/migrations/0001_initial.py
django_http_debug/migrations/0002_debugendpoint_content_type_debugendpoint_is_base64.py
django_http_debug/migrations/0003_requestlog_query_string.py
django_http_debug/migrations/0004_debugendpoint_logging_enabled.py
django_http_debug/migrations/__init__.py
django_http_debug-0.2.dist-info/LICENSE
django_http_debug-0.2.dist-info/METADATA
django_http_debug-0.2.dist-info/WHEEL
django_http_debug-0.2.dist-info/top_level.txt
django_http_debug-0.2.dist-info/RECORD
