Metadata-Version: 2.1
Name: django-http-debug
Version: 0.2
Summary: Django app for creating database-backed HTTP debug endpoints
Author: Simon Willison
License: Apache-2.0
Project-URL: Homepage, https://github.com/simonw/django-http-debug
Project-URL: Changelog, https://github.com/simonw/django-http-debug/releases
Project-URL: Issues, https://github.com/simonw/django-http-debug/issues
Project-URL: CI, https://github.com/simonw/django-http-debug/actions
Classifier: License :: OSI Approved :: Apache Software License
Requires-Python: >=3.8
License-File: LICENSE
Requires-Dist: filetype
Requires-Dist: django
Provides-Extra: test
Requires-Dist: pytest ; extra == 'test'
